os_resource_classes/__init__.py
os_resource_classes/tests/__init__.py
os_resource_classes/tests/base.py
os_resource_classes/tests/test_os_resource_classes.py
os_resource_classes-1.1.0.dist-info/AUTHORS
os_resource_classes-1.1.0.dist-info/LICENSE
os_resource_classes-1.1.0.dist-info/METADATA
os_resource_classes-1.1.0.dist-info/WHEEL
os_resource_classes-1.1.0.dist-info/pbr.json
os_resource_classes-1.1.0.dist-info/top_level.txt
os_resource_classes-1.1.0.dist-info/RECORD
